sphecerix/__init__.py
sphecerix/_version.py
sphecerix/atomic_wave_functions.py
sphecerix/basis_functions.py
sphecerix/character_table.py
sphecerix/matrixplot.py
sphecerix/molecule.py
sphecerix/projection_operator.py
sphecerix/symmetry_operations.py
sphecerix/tesseral.py
sphecerix/wignerd.py
sphecerix/charactertables/c3v.json
sphecerix/charactertables/d2h.json
sphecerix/charactertables/d6h.json
sphecerix/charactertables/ih.json
sphecerix/charactertables/td.json
sphecerix-0.6.1.dist-info/METADATA
sphecerix-0.6.1.dist-info/WHEEL
sphecerix-0.6.1.dist-info/top_level.txt
sphecerix-0.6.1.dist-info/RECORD
