Metadata-Version: 2.2
Name: sphecerix
Version: 0.6.1
Summary: sphecerix
Home-page: https://github.com/ifilot/sphecerix
Author: Ivo Filot
Author-email: Ivo Filot <ivo@ivofilot.nl>
Maintainer-email: Ivo Filot <ivo@ivofilot.nl>
License: GPL-3.0-or-later
Project-URL: Homepage, https://github.com/ifilot/sphecerix
Project-URL: Bug Tracker, https://github.com/ifilot/sphecerix/issues
Classifier: Programming Language :: Python :: 3
Classifier: Operating System :: OS Independent
Requires-Python: >=3.5
Requires-Dist: scipy>=1.15
Requires-Dist: numpy
Requires-Dist: pyqint
Requires-Dist: pylebedev
Requires-Dist: matplotlib
Requires-Dist: networkx
Dynamic: author
Dynamic: home-page
Dynamic: requires-python
